llamabot/__init__.py
llamabot/code_manipulation.py
llamabot/config.py
llamabot/doc_processor.py
llamabot/dummy.py
llamabot/experiments.py
llamabot/file_finder.py
llamabot/mcp_server.py
llamabot/prompt_manager.py
llamabot/recorder.py
llamabot/schemas.py
llamabot/utils.py
llamabot/version.py
llamabot/bot/__init__.py
llamabot/bot/agentbot.py
llamabot/bot/imagebot.py
llamabot/bot/kgbot.py
llamabot/bot/model_tokens.py
llamabot/bot/ollama_model_names.txt
llamabot/bot/qabot.py
llamabot/bot/querybot.py
llamabot/bot/simplebot.py
llamabot/bot/structuredbot.py
llamabot/bot/toolbot.py
llamabot/cli/__init__.py
llamabot/cli/blog.py
llamabot/cli/configure.py
llamabot/cli/doc.py
llamabot/cli/docs.py
llamabot/cli/git.py
llamabot/cli/logviewer.py
llamabot/cli/mcp.py
llamabot/cli/notebook.py
llamabot/cli/repo.py
llamabot/cli/tutorial.py
llamabot/cli/utils.py
llamabot/components/__init__.py
llamabot/components/api.py
llamabot/components/chatui.py
llamabot/components/context_engineering.py
llamabot/components/docstore.py
llamabot/components/history.py
llamabot/components/messages.py
llamabot/components/sandbox.py
llamabot/components/tools.py
llamabot/components/chat_memory/__init__.py
llamabot/components/chat_memory/memory.py
llamabot/components/chat_memory/models.py
llamabot/components/chat_memory/retrieval.py
llamabot/components/chat_memory/selectors.py
llamabot/components/chat_memory/storage.py
llamabot/components/chat_memory/visualization.py
llamabot/components/pocketflow/__init__.py
llamabot/components/pocketflow/nodes.py
llamabot/components/pocketflow/visualization.py
llamabot/data/mcp_docs/llamabot-docs.lance/_indices/20753d4e-330f-48fc-b705-7f79b736a212/metadata.lance
llamabot/data/mcp_docs/llamabot-docs.lance/_indices/314f19ae-19d2-4305-9185-0f1bb1682fc5/metadata.lance
llamabot/data/mcp_docs/llamabot-docs.lance/_indices/314f19ae-19d2-4305-9185-0f1bb1682fc5/part_1_docs.lance
llamabot-0.17.3.dist-info/METADATA
llamabot-0.17.3.dist-info/WHEEL
llamabot-0.17.3.dist-info/entry_points.txt
llamabot-0.17.3.dist-info/RECORD
