Metadata-Version: 2.4
Name: llamabot
Version: 0.17.3
Summary: A Pythonic interface to LLMs.
Project-URL: Documentation, https://ericmjl.github.io/llamabot
Project-URL: Source Code, https://github.com/ericmjl/llamabot
Requires-Python: <3.13,>=3.9
Requires-Dist: beautifulsoup4
Requires-Dist: chonkie
Requires-Dist: docstring-parser<0.18,>=0.17.0
Requires-Dist: duckduckgo-search
Requires-Dist: fastapi>=0.115.9
Requires-Dist: fastmcp
Requires-Dist: httpx
Requires-Dist: jinja2
Requires-Dist: litellm>=1.71.0
Requires-Dist: loguru
Requires-Dist: networkx
Requires-Dist: numpy
Requires-Dist: numpydoc
Requires-Dist: openai
Requires-Dist: pdfminer-six
Requires-Dist: pocketflow
Requires-Dist: pydantic>=2.0
Requires-Dist: pyprojroot
Requires-Dist: python-dotenv
Requires-Dist: python-frontmatter
Requires-Dist: python-multipart
Requires-Dist: python-slugify
Requires-Dist: sqlalchemy
Requires-Dist: starlette
Requires-Dist: tenacity
Requires-Dist: tqdm
Requires-Dist: typer>=0.15.3
Requires-Dist: uvicorn
Provides-Extra: agent
Requires-Dist: docker; extra == 'agent'
Requires-Dist: markdownify; extra == 'agent'
Provides-Extra: all
Requires-Dist: case-converter; extra == 'all'
Requires-Dist: docker; extra == 'all'
Requires-Dist: gitpython; extra == 'all'
Requires-Dist: ics; extra == 'all'
Requires-Dist: ipykernel; extra == 'all'
Requires-Dist: lancedb>=0.22; extra == 'all'
Requires-Dist: markdownify; extra == 'all'
Requires-Dist: modal; extra == 'all'
Requires-Dist: nbformat; extra == 'all'
Requires-Dist: prompt-toolkit; extra == 'all'
Requires-Dist: pylance; extra == 'all'
Requires-Dist: pyperclip; extra == 'all'
Requires-Dist: python-frontmatter; extra == 'all'
Requires-Dist: rank-bm25; extra == 'all'
Requires-Dist: rerankers; extra == 'all'
Requires-Dist: rich; extra == 'all'
Requires-Dist: sentence-transformers; extra == 'all'
Requires-Dist: tzlocal; extra == 'all'
Provides-Extra: cli
Requires-Dist: case-converter; extra == 'cli'
Requires-Dist: gitpython; extra == 'cli'
Requires-Dist: nbformat; extra == 'cli'
Requires-Dist: prompt-toolkit; extra == 'cli'
Requires-Dist: pyperclip; extra == 'cli'
Requires-Dist: python-frontmatter; extra == 'cli'
Requires-Dist: rich; extra == 'cli'
Provides-Extra: notebooks
Requires-Dist: ics; extra == 'notebooks'
Requires-Dist: ipykernel; extra == 'notebooks'
Requires-Dist: modal; extra == 'notebooks'
Requires-Dist: tzlocal; extra == 'notebooks'
Provides-Extra: rag
Requires-Dist: lancedb>=0.22; extra == 'rag'
Requires-Dist: pylance; extra == 'rag'
Requires-Dist: rank-bm25; extra == 'rag'
Requires-Dist: rerankers; extra == 'rag'
Requires-Dist: sentence-transformers; extra == 'rag'
